LICENSE
README.md
setup.py
tap_mailchimp/__init__.py
tap_mailchimp/client.py
tap_mailchimp/discover.py
tap_mailchimp/schema.py
tap_mailchimp/sync.py
tap_mailchimp.egg-info/PKG-INFO
tap_mailchimp.egg-info/SOURCES.txt
tap_mailchimp.egg-info/dependency_links.txt
tap_mailchimp.egg-info/entry_points.txt
tap_mailchimp.egg-info/requires.txt
tap_mailchimp.egg-info/top_level.txt
tap_mailchimp/schemas/automations.json
tap_mailchimp/schemas/campaigns.json
tap_mailchimp/schemas/list_members.json
tap_mailchimp/schemas/list_segment_members.json
tap_mailchimp/schemas/list_segments.json
tap_mailchimp/schemas/lists.json
tap_mailchimp/schemas/reports_email_activity.json
tap_mailchimp/schemas/unsubscribes.json