Metadata-Version: 2.1
Name: tap-mailchimp
Version: 1.3.0
Summary: Singer.io tap for extracting data from the Mailchimp API
Home-page: https://singer.io
Author: Stitch
Classifier: Programming Language :: Python :: 3 :: Only
Provides-Extra: dev
License-File: LICENSE
